_quickfix.cpython-38-x86_64-linux-gnu.so
quickfix.py
quickfix40.py
quickfix41.py
quickfix42.py
quickfix43.py
quickfix44.py
quickfix50.py
quickfix50sp1.py
quickfix50sp2.py
quickfixt11.py
quickfix_ssl-1.15.1.post4.data/data/share/quickfix/FIX40.xml
quickfix_ssl-1.15.1.post4.data/data/share/quickfix/FIX41.xml
quickfix_ssl-1.15.1.post4.data/data/share/quickfix/FIX42.xml
quickfix_ssl-1.15.1.post4.data/data/share/quickfix/FIX43.xml
quickfix_ssl-1.15.1.post4.data/data/share/quickfix/FIX44.xml
quickfix_ssl-1.15.1.post4.data/data/share/quickfix/FIX50.xml
quickfix_ssl-1.15.1.post4.data/data/share/quickfix/FIX50SP1.xml
quickfix_ssl-1.15.1.post4.data/data/share/quickfix/FIX50SP2.xml
quickfix_ssl-1.15.1.post4.data/data/share/quickfix/FIXT11.xml
quickfix_ssl-1.15.1.post4.dist-info/LICENSE
quickfix_ssl-1.15.1.post4.dist-info/METADATA
quickfix_ssl-1.15.1.post4.dist-info/WHEEL
quickfix_ssl-1.15.1.post4.dist-info/top_level.txt
quickfix_ssl-1.15.1.post4.dist-info/RECORD
quickfix_ssl.libs/libk5crypto-b1f99d5c.so.3.1
quickfix_ssl.libs/libkrb5-6824148d.so.3.3
quickfix_ssl.libs/libpcre-9513aab5.so.1.2.0
quickfix_ssl.libs/libkrb5support-f4e34ad2.so.0.1
quickfix_ssl.libs/libcom_err-2abe824b.so.2.1
quickfix_ssl.libs/libselinux-0922c95c.so.1
quickfix_ssl.libs/libcrypto-19957f5b.so.1.0.2k
quickfix_ssl.libs/libgssapi_krb5-497db0c6.so.2.2
quickfix_ssl.libs/libkeyutils-dfe70bd6.so.1.5
quickfix_ssl.libs/libssl-2a9eae6f.so.1.0.2k
