Metadata-Version: 2.1
Name: quickfix-ssl
Version: 1.15.1.post4
Summary: FIX (Financial Information eXchange) protocol implementation (SSL enabled)
Home-page: http://www.quickfixengine.org
Author: Oren Miller
Author-email: oren@quickfixengine.org
Maintainer: Mark Lee
Maintainer-email: mark.lee@droveend.com
License: UNKNOWN
Download-URL: http://www.quickfixengine.org
Platform: UNKNOWN
